01_Async_FIFO_CDC/rptr_empty.v
`timescale 1ns/1ps

module rptr_empty
#(
    parameter ADDRSIZE = 4
)
(
    input  wire                  rclk,
    input  wire                  rrst_n,
    input  wire                  rinc,

    input  wire [ADDRSIZE:0]     rq2_wptr,

    output reg                   rempty,

    output reg  [ADDRSIZE:0]     rptr,
    output reg  [ADDRSIZE:0]     rbin,

    output wire [ADDRSIZE-1:0]   raddr
);

    //------------------------------------------
    // Next Pointer Values
    //------------------------------------------

    wire [ADDRSIZE:0] rbinnext;
    wire [ADDRSIZE:0] rgraynext;

    wire              rempty_val;

    //------------------------------------------
    // Memory Address
    //------------------------------------------

    assign raddr = rbin[ADDRSIZE-1:0];

    //------------------------------------------
    // Binary Pointer Increment
    //------------------------------------------

    assign rbinnext = rbin + (rinc & ~rempty);

    //------------------------------------------
    // Binary → Gray Conversion
    //------------------------------------------

    assign rgraynext = (rbinnext >> 1) ^ rbinnext;

    //------------------------------------------
    // Empty Detection
    //------------------------------------------

    assign rempty_val = (rgraynext == rq2_wptr);

    //------------------------------------------
    // Pointer Registers
    //------------------------------------------

    always @(posedge rclk or negedge rrst_n)
    begin
        if(!rrst_n)
        begin
            rbin   <= 0;
            rptr   <= 0;
            rempty <= 1'b1;
        end
        else
        begin
            rbin   <= rbinnext;
            rptr   <= rgraynext;
            rempty <= rempty_val;
        end
    end

endmodule

01_Async_FIFO_CDC/wptr_full.v
`timescale 1ns/1ps

module wptr_full
#(
    parameter ADDRSIZE = 4
)
(
    input  wire                  wclk,
    input  wire                  wrst_n,
    input  wire                  winc,

    input  wire [ADDRSIZE:0]     wq2_rptr,

    output reg                   wfull,

    output reg  [ADDRSIZE:0]     wptr,
    output reg  [ADDRSIZE:0]     wbin,

    output wire [ADDRSIZE-1:0]   waddr
);

    //------------------------------------------
    // Next Pointer Values
    //------------------------------------------

    wire [ADDRSIZE:0] wbinnext;
    wire [ADDRSIZE:0] wgraynext;

    wire              wfull_val;

    //------------------------------------------
    // Memory Address
    //------------------------------------------

    assign waddr = wbin[ADDRSIZE-1:0];

    //------------------------------------------
    // Binary Pointer Increment
    //------------------------------------------

    assign wbinnext = wbin + (winc & ~wfull);

    //------------------------------------------
    // Binary → Gray
    //------------------------------------------

    assign wgraynext = (wbinnext >> 1) ^ wbinnext;

        //------------------------------------------
    // Full Detection
    //------------------------------------------

    assign wfull_val =
        (wgraynext ==
        {
            ~wq2_rptr[ADDRSIZE:ADDRSIZE-1],
             wq2_rptr[ADDRSIZE-2:0]
        });

    //------------------------------------------
    // Pointer Registers
    //------------------------------------------

    always @(posedge wclk or negedge wrst_n)
    begin
        if(!wrst_n)
        begin
            wbin  <= 0;
            wptr  <= 0;
            wfull <= 1'b0;
        end
        else
        begin
            wbin  <= wbinnext;
            wptr  <= wgraynext;
            wfull <= wfull_val;
        end
    end

endmodule

01_Async_FIFO_CDC/sync_w2r.v
`timescale 1ns/1ps

module sync_w2r
#(
    parameter ADDRSIZE = 4
)
(
    input  wire                  rclk,
    input  wire                  rrst_n,

    input  wire [ADDRSIZE:0]     wptr,

    output reg  [ADDRSIZE:0]     rq2_wptr
);

    reg [ADDRSIZE:0] rq1_wptr;

    //------------------------------------------
    // Two Flip-Flop Synchronizer
    //------------------------------------------

    always @(posedge rclk or negedge rrst_n)
    begin
        if(!rrst_n)
        begin
            rq1_wptr <= 0;
            rq2_wptr <= 0;
        end
        else
        begin
            rq1_wptr <= wptr;
            rq2_wptr <= rq1_wptr;
        end
    end

endmodule

01_Async_FIFO_CDC/sync_r2w.v
`timescale 1ns/1ps

module sync_r2w
#(
    parameter ADDRSIZE = 4
)
(
    input  wire                  wclk,
    input  wire                  wrst_n,

    input  wire [ADDRSIZE:0]     rptr,

    output reg  [ADDRSIZE:0]     wq2_rptr
);

    reg [ADDRSIZE:0] wq1_rptr;

    //------------------------------------------
    // Two Flip-Flop Synchronizer
    //------------------------------------------

    always @(posedge wclk or negedge wrst_n)
    begin
        if(!wrst_n)
        begin
            wq1_rptr <= 0;
            wq2_rptr <= 0;
        end
        else
        begin
            wq1_rptr <= rptr;
            wq2_rptr <= wq1_rptr;
        end
    end

endmodule

01_Async_FIFO_CDC/fifomem.v
`timescale 1ns/1ps

module fifomem
#(
    parameter DATASIZE = 8,
    parameter ADDRSIZE = 4
)
(
    input  wire                     wclk,
    input  wire                     wclken,
    input  wire                     wfull,

    input  wire [ADDRSIZE-1:0]      waddr,
    input  wire [ADDRSIZE-1:0]      raddr,

    input  wire [DATASIZE-1:0]      wdata,

    output wire [DATASIZE-1:0]      rdata
);

    //---------------------------------------------------
    // Memory Declaration
    //---------------------------------------------------

    reg [DATASIZE-1:0] mem [0:(1<<ADDRSIZE)-1];

    //---------------------------------------------------
    // Write Logic
    //---------------------------------------------------

    always @(posedge wclk)
    begin
        if(wclken && !wfull)
            mem[waddr] <= wdata;
    end

    //---------------------------------------------------
    // Read Logic
    //---------------------------------------------------

    assign rdata = mem[raddr];

endmodule

01_Async_FIFO_CDC/async_fifo.v
`timescale 1ns/1ps

module async_fifo
#(
    parameter DATASIZE = 8,
    parameter ADDRSIZE = 4
)
(
    // Write Interface
    input  wire                  wclk,
    input  wire                  wrst_n,
    input  wire                  winc,
    input  wire [DATASIZE-1:0]   wdata,
    output wire                  wfull,

    // Read Interface
    input  wire                  rclk,
    input  wire                  rrst_n,
    input  wire                  rinc,
    output wire [DATASIZE-1:0]   rdata,
    output wire                  rempty
);

    //----------------------------------------
    // Internal Signals
    //----------------------------------------

    wire [ADDRSIZE:0] wptr;
    wire [ADDRSIZE:0] rptr;

    wire [ADDRSIZE:0] wbin;
    wire [ADDRSIZE:0] rbin;

    wire [ADDRSIZE-1:0] waddr;
    wire [ADDRSIZE-1:0] raddr;

    wire [ADDRSIZE:0] wq2_rptr;
    wire [ADDRSIZE:0] rq2_wptr;

        fifomem
    #(
        .DATASIZE(DATASIZE),
        .ADDRSIZE(ADDRSIZE)
    )
    u_mem
    (
        .wclk(wclk),
        .wclken(winc),
        .wfull(wfull),

        .waddr(waddr),
        .raddr(raddr),

        .wdata(wdata),
        .rdata(rdata)
    );

        sync_r2w
    #(
        .ADDRSIZE(ADDRSIZE)
    )
    u_sync_r2w
    (
        .wclk(wclk),
        .wrst_n(wrst_n),

        .rptr(rptr),

        .wq2_rptr(wq2_rptr)
    );

        sync_w2r
    #(
        .ADDRSIZE(ADDRSIZE)
    )
    u_sync_w2r
    (
        .rclk(rclk),
        .rrst_n(rrst_n),

        .wptr(wptr),

        .rq2_wptr(rq2_wptr)
    );

        wptr_full
    #(
        .ADDRSIZE(ADDRSIZE)
    )
    u_wptr
    (
        .wclk(wclk),
        .wrst_n(wrst_n),
        .winc(winc),

        .wq2_rptr(wq2_rptr),

        .wfull(wfull),

        .wptr(wptr),
        .wbin(wbin),

        .waddr(waddr)
    );

        rptr_empty
    #(
        .ADDRSIZE(ADDRSIZE)
    )
    u_rptr
    (
        .rclk(rclk),
        .rrst_n(rrst_n),
        .rinc(rinc),

        .rq2_wptr(rq2_wptr),

        .rempty(rempty),

        .rptr(rptr),
        .rbin(rbin),

        .raddr(raddr)
    );

endmodule

01_Async_FIFO_CDC/tb_async_fifo.v
`timescale 1ns/1ps

module tb_async_fifo;

parameter DATASIZE = 8;
parameter ADDRSIZE = 4;

//--------------------------------------
// DUT Signals
//--------------------------------------

reg wclk;
reg rclk;

reg wrst_n;
reg rrst_n;

reg winc;
reg rinc;

reg [DATASIZE-1:0] wdata;

wire [DATASIZE-1:0] rdata;

wire wfull;
wire rempty;

//--------------------------------------
// DUT
//--------------------------------------

async_fifo
#(
    .DATASIZE(DATASIZE),
    .ADDRSIZE(ADDRSIZE)
)
dut
(
    .wclk(wclk),
    .wrst_n(wrst_n),
    .winc(winc),
    .wdata(wdata),
    .wfull(wfull),

    .rclk(rclk),
    .rrst_n(rrst_n),
    .rinc(rinc),
    .rdata(rdata),
    .rempty(rempty)
);

//--------------------------------------
// Write Clock (100 MHz)
//--------------------------------------

initial
begin
    wclk = 0;
    forever #5 wclk = ~wclk;
end

//--------------------------------------
// Read Clock (71.4 MHz)
//--------------------------------------

initial
begin
    rclk = 0;
    forever #7 rclk = ~rclk;
end

//--------------------------------------
// Dump Waves
//--------------------------------------

initial
begin
    $dumpfile("fifo.vcd");
    $dumpvars(0,tb_async_fifo);
end

//--------------------------------------
// Test Sequence
//--------------------------------------

integer i;

initial
begin

    wrst_n = 0;
    rrst_n = 0;

    winc = 0;
    rinc = 0;

    wdata = 0;

    #30;

    wrst_n = 1;
    rrst_n = 1;

    //----------------------------------
    // WRITE 8 VALUES
    //----------------------------------

    for(i=0;i<8;i=i+1)
    begin

        @(posedge wclk);

        if(!wfull)
        begin
            winc = 1;
            wdata = i + 8'h11;

            $display(
            "[WRITE] Time=%0t Data=%h",
            $time,
            wdata
            );
        end

    end

    @(posedge wclk);
    winc = 0;

//----------------------------------
// Wait for synchronization
//----------------------------------

repeat(3) @(posedge rclk);

//----------------------------------
// READ 8 VALUES
//----------------------------------

for(i=0;i<8;i=i+1)
begin

    @(posedge rclk);

    if(!rempty)
    begin
        rinc = 1;
    end

    @(posedge rclk);

    rinc = 0;

    #1;

    $display(
        "[READ ] Time=%0t Data=%h",
        $time,
        rdata
    );

end

    @(posedge rclk);
    rinc = 0;

    #100;

    $finish;

end

endmodule

01_Async_FIFO_CDC/fifo.vcd
$date
	Sat Jul 18 11:38:57 2026
$end
$version
	Icarus Verilog
$end
$timescale
	1ps
$end
$scope module tb_async_fifo $end
$var wire 1 ! wfull $end
$var wire 1 " rempty $end
$var wire 8 # rdata [7:0] $end
$var reg 1 $ rclk $end
$var reg 1 % rinc $end
$var reg 1 & rrst_n $end
$var reg 1 ' wclk $end
$var reg 8 ( wdata [7:0] $end
$var reg 1 ) winc $end
$var reg 1 * wrst_n $end
$var integer 32 + i [31:0] $end
$scope module dut $end
$var wire 1 $ rclk $end
$var wire 1 % rinc $end
$var wire 1 & rrst_n $end
$var wire 1 ' wclk $end
$var wire 8 , wdata [7:0] $end
$var wire 1 ) winc $end
$var wire 1 * wrst_n $end
$var wire 5 - wq2_rptr [4:0] $end
$var wire 5 . wptr [4:0] $end
$var wire 1 ! wfull $end
$var wire 5 / wbin [4:0] $end
$var wire 4 0 waddr [3:0] $end
$var wire 5 1 rq2_wptr [4:0] $end
$var wire 5 2 rptr [4:0] $end
$var wire 1 " rempty $end
$var wire 8 3 rdata [7:0] $end
$var wire 5 4 rbin [4:0] $end
$var wire 4 5 raddr [3:0] $end
$scope module u_mem $end
$var wire 8 6 rdata [7:0] $end
$var wire 1 ' wclk $end
$var wire 1 ) wclken $end
$var wire 8 7 wdata [7:0] $end
$var wire 1 ! wfull $end
$var wire 4 8 waddr [3:0] $end
$var wire 4 9 raddr [3:0] $end
$upscope $end
$scope module u_rptr $end
$var wire 1 $ rclk $end
$var wire 5 : rgraynext [4:0] $end
$var wire 1 % rinc $end
$var wire 1 & rrst_n $end
$var wire 5 ; rq2_wptr [4:0] $end
$var wire 1 < rempty_val $end
$var wire 5 = rbinnext [4:0] $end
$var wire 4 > raddr [3:0] $end
$var reg 5 ? rbin [4:0] $end
$var reg 1 " rempty $end
$var reg 5 @ rptr [4:0] $end
$upscope $end
$scope module u_sync_r2w $end
$var wire 5 A rptr [4:0] $end
$var wire 1 ' wclk $end
$var wire 1 * wrst_n $end
$var reg 5 B wq1_rptr [4:0] $end
$var reg 5 C wq2_rptr [4:0] $end
$upscope $end
$scope module u_sync_w2r $end
$var wire 1 $ rclk $end
$var wire 1 & rrst_n $end
$var wire 5 D wptr [4:0] $end
$var reg 5 E rq1_wptr [4:0] $end
$var reg 5 F rq2_wptr [4:0] $end
$upscope $end
$scope module u_wptr $end
$var wire 1 ' wclk $end
$var wire 5 G wgraynext [4:0] $end
$var wire 1 ) winc $end
$var wire 5 H wq2_rptr [4:0] $end
$var wire 1 * wrst_n $end
$var wire 1 I wfull_val $end
$var wire 5 J wbinnext [4:0] $end
$var wire 4 K waddr [3:0] $end
$var reg 5 L wbin [4:0] $end
$var reg 1 ! wfull $end
$var reg 5 M wptr [4:0] $end
$upscope $end
$upscope $end
$upscope $end
$enddefinitions $end
#0
$dumpvars
b0 M
b0 L
b0 K
b0 J
0I
b0 H
b0 G
b0 F
b0 E
b0 D
b0 C
b0 B
b0 A
b0 @
b0 ?
b0 >
b0 =
1<
b0 ;
b0 :
b0 9
b0 8
b0 7
bx 6
b0 5
b0 4
bx 3
b0 2
b0 1
b0 0
b0 /
b0 .
b0 -
b0 ,
bx +
0*
0)
b0 (
0'
0&
0%
0$
bx #
1"
0!
$end
#5000
1'
#7000
1$
#10000
0'
#14000
0$
#15000
1'
#20000
0'
#21000
1$
#25000
1'
#28000
0$
#30000
0'
b0 +
1&
1*
#35000
b10001 #
b10001 3
b10001 6
b1 G
b1 J
b1 +
b10001 (
b10001 ,
b10001 7
1)
1'
1$
#40000
0'
#42000
0$
#45000
b1 0
b1 8
b1 K
b11 G
b1 .
b1 D
b1 M
b10 J
b1 /
b1 L
b10 +
b10010 (
b10010 ,
b10010 7
1'
#49000
b1 E
1$
#50000
0'
#55000
b10 0
b10 8
b10 K
b10 G
b11 .
b11 D
b11 M
b11 J
b10 /
b10 L
b11 +
b10011 (
b10011 ,
b10011 7
1'
#56000
0$
#60000
0'
#63000
0<
b1 1
b1 ;
b1 F
b11 E
1$
#65000
b11 0
b11 8
b11 K
b110 G
b10 .
b10 D
b10 M
b100 J
b11 /
b11 L
b100 +
b10100 (
b10100 ,
b10100 7
1'
#70000
0'
0$
#75000
b100 0
b100 8
b100 K
b111 G
b110 .
b110 D
b110 M
b101 J
b100 /
b100 L
b101 +
b10101 (
b10101 ,
b10101 7
1'
#77000
b11 1
b11 ;
b11 F
b110 E
0"
1$
#80000
0'
#84000
0$
#85000
b101 0
b101 8
b101 K
b101 G
b111 .
b111 D
b111 M
b110 J
b101 /
b101 L
b110 +
b10110 (
b10110 ,
b10110 7
1'
#90000
0'
#91000
b110 1
b110 ;
b110 F
b111 E
1$
#95000
b110 0
b110 8
b110 K
b100 G
b101 .
b101 D
b101 M
b111 J
b110 /
b110 L
b111 +
b10111 (
b10111 ,
b10111 7
1'
#98000
0$
#100000
0'
#105000
b111 0
b111 8
b111 K
b1100 G
b100 .
b100 D
b100 M
b1000 J
b111 /
b111 L
b111 1
b111 ;
b111 F
b101 E
b1000 +
b11000 (
b11000 ,
b11000 7
1'
1$
#110000
0'
#112000
0$
#115000
b1000 0
b1000 8
b1000 K
b1100 .
b1100 D
b1100 M
b1000 /
b1000 L
b1100 G
b1000 J
0)
1'
#119000
b101 1
b101 ;
b101 F
b1100 E
1$
#120000
0'
#125000
1'
#126000
0$
#130000
0'
#133000
b1100 1
b1100 ;
b1100 F
1$
#135000
1'
#140000
0'
0$
#145000
1'
#147000
b0 +
1$
#150000
0'
#154000
0$
#155000
1'
#160000
0'
#161000
b1 :
b1 =
1%
1$
#165000
1'
#168000
0$
#170000
0'
#175000
b10011 #
b10011 3
b10011 6
b1 5
b1 9
b1 >
b1 2
b1 @
b1 A
b1 4
b1 ?
b1 :
b1 =
0%
1'
1$
#176000
b1 +
#180000
0'
#182000
0$
#185000
b1 B
1'
#189000
b11 :
b10 =
1%
1$
#190000
0'
#195000
b1 -
b1 C
b1 H
1'
#196000
0$
#200000
0'
#203000
b10 5
b10 9
b10 >
b11 2
b11 @
b11 A
b10 4
b10 ?
b11 :
b10 =
0%
1$
#204000
b10 +
#205000
b11 B
1'
#210000
0'
0$
#215000
b11 -
b11 C
b11 H
1'
#217000
b10 :
b11 =
1%
1$
#220000
0'
#224000
0$
#225000
1'
#230000
0'
#231000
b10101 #
b10101 3
b10101 6
b11 5
b11 9
b11 >
b10 2
b10 @
b10 A
b11 4
b11 ?
b10 :
b11 =
0%
1$
#232000
b11 +
#235000
b10 B
1'
#238000
0$
#240000
0'
#245000
b10 -
b10 C
b10 H
b110 :
b100 =
1%
1'
1$
#250000
0'
#252000
0$
#255000
1'
#259000
b100 5
b100 9
b100 >
b110 2
b110 @
b110 A
b100 4
b100 ?
b110 :
b100 =
0%
1$
#260000
b100 +
0'
#265000
b110 B
1'
#266000
0$
#270000
0'
#273000
b111 :
b101 =
1%
1$
#275000
b110 -
b110 C
b110 H
1'
#280000
0'
0$
#285000
1'
#287000
b10111 #
b10111 3
b10111 6
b101 5
b101 9
b101 >
b111 2
b111 @
b111 A
b101 4
b101 ?
b111 :
b101 =
0%
1$
#288000
b101 +
#290000
0'
#294000
0$
#295000
b111 B
1'
#300000
0'
#301000
b101 :
b110 =
1%
1$
#305000
b111 -
b111 C
b111 H
1'
#308000
0$
#310000
0'
#315000
b110 5
b110 9
b110 >
b101 2
b101 @
b101 A
b110 4
b110 ?
b101 :
b110 =
0%
1'
1$
#316000
b110 +
#320000
0'
#322000
0$
#325000
b101 B
1'
#329000
b100 :
b111 =
1%
1$
#330000
0'
#335000
b101 -
b101 C
b101 H
1'
#336000
0$
#340000
0'
#343000
bx #
bx 3
bx 6
b111 5
b111 9
b111 >
b100 2
b100 @
b100 A
b111 4
b111 ?
b100 :
b111 =
0%
1$
#344000
b111 +
#345000
b100 B
1'
#350000
0'
0$
#355000
b100 -
b100 C
b100 H
1'
#357000
1<
b1100 :
b1000 =
1%
1$
#360000
0'
#364000
0$
#365000
1'
#370000
0'
#371000
b1000 5
b1000 9
b1000 >
1"
b1100 2
b1100 @
b1100 A
b1000 4
b1000 ?
1<
b1100 :
b1000 =
0%
1$
#372000
b1000 +
#375000
b1100 B
1'
#378000
0$
#380000
0'
#385000
b1100 -
b1100 C
b1100 H
1'
1$
