05_UART_Tx_Rx/UART_Rx.v
`timescale 1ns / 1ps

module UART_Rx(input clk,
				input rst,
				input rx_serial,
				output reg done,
				output reg[7:0]rx_data
    );
	parameter baudrate=115200, clk_freq=49_500_000;
	parameter clk_perbit=clk_freq/baudrate;
	parameter half_clk = clk_perbit>>1;
	parameter idle=0,start=1,transfer=2,stop=3;
	reg [15:0]count;
	reg [2:0]bit_count;
	reg [7:0]rx_reg;
	reg [1:0]state;
	
	
	always@(posedge clk or posedge rst)begin
		if(rst)begin
			done<=0;
			rx_reg<=0;
			rx_data<=0;
			state<=idle;
		end
		else begin
			case(state)
				idle:begin
					state<=(rx_serial==1)?idle:start;
					done<=0;
					count<=0;
					bit_count<=0;
					rx_reg<=0;
				end
				start:begin
					if(count==half_clk-1)begin
						state<=(rx_serial==0)?transfer:idle;
						count<=0;
					end					
					else
						count<=count+1;
				end
				transfer:begin
					if(count==clk_perbit-1)begin
						count<=0;
						rx_reg[bit_count]<=rx_serial;
						if(bit_count<7)
							bit_count<=bit_count+1;
						else begin
							bit_count<=0;
							state<=stop;
						end
					end 
					else
						count<=count+1;
				end
				stop:begin
					if(count==clk_perbit-1)begin
						if(rx_serial==1)begin
							rx_data<=rx_reg;
							done<=1;
						end
						state<=idle;
					end
					else
						count<=count+1;
				end
			endcase
		end
	end
	
	
	
endmodule

05_UART_Tx_Rx/UART_Tx.v
`timescale 1ns / 1ps


module UART_Tx(input clk,
                input rst,
                input tx_st,
                input [7:0]tx_data,
                output tx_busy,
                output tx_serial);
    
    parameter baudrate=115200,clk_freq=50_000_000;
    parameter clk_perbit=clk_freq/baudrate;
    parameter idle=0, start=1, transfer=2, stop=3;
    reg [1:0]state;
    reg [15:0]count;
    reg [2:0]bit_count;
	reg [7:0]tx_reg;
	
    
    always@(posedge clk or posedge rst)begin
        if(rst)begin
            state<=idle;
			count<=0;
			bit_count<=0;
			tx_reg<=0;

		end
        else begin
			case(state)
				idle:begin
					count<=0;
					bit_count<=0;
					state<=(tx_st==1)?start:idle;					
				end
				start:begin
					tx_reg<=tx_data;
					if(count<clk_perbit-1)
						count<=count+1;
					else begin
						count<=0;
						state<=transfer;
	
					end

				end
				transfer:begin

					if(count<clk_perbit-1)
						count<=count+1;
					else begin
						count<=0;
						if(bit_count<7)
							bit_count<=bit_count+1;
						else begin
							bit_count<=0;
							state<=stop;
						end
					end
				end
				stop:begin
					if(count<clk_perbit-1)
						count<=count+1;
					else begin
						count<=0;
						state<=idle;
					end

				end
			endcase
		end
	end
	

	assign tx_busy=(~(state==idle))&(~rst);
	assign tx_serial=(state==start)?0:((state==transfer)?tx_reg[bit_count]:1);
     
    
endmodule

05_UART_Tx_Rx/UART_tb.v
`timescale 1ns/1ps

module UART_tb;

    // Inputs
    reg clk;
    reg rst;
    reg tx_st;
    reg [7:0] tx_data;

    // Outputs
    wire tx_busy;
    wire tx_serial;
    wire done;
    wire [7:0] rx_data;

    //-------------------------------------------------
    // Clock Generation (50 MHz)
    //-------------------------------------------------
    initial begin
        clk = 0;
        forever #10 clk = ~clk;      // 20 ns period
    end

    //-------------------------------------------------
    // UART Transmitter
    //-------------------------------------------------
    UART_Tx uut_tx (
        .clk(clk),
        .rst(rst),
        .tx_st(tx_st),
        .tx_data(tx_data),
        .tx_busy(tx_busy),
        .tx_serial(tx_serial)
    );

    //-------------------------------------------------
    // UART Receiver
    //-------------------------------------------------
    UART_Rx uut_rx (
        .clk(clk),
        .rst(rst),
        .rx_serial(tx_serial),
        .done(done),
        .rx_data(rx_data)
    );

    //-------------------------------------------------
    // Dump Waveform
    //-------------------------------------------------
    initial begin
        $dumpfile("uart.vcd");
        $dumpvars(0, UART_tb);
    end

    //-------------------------------------------------
    // Test Stimulus
    //-------------------------------------------------
    initial begin

        // Initialize
        rst     = 1;
        tx_st   = 0;
        tx_data = 8'h00;

        // Reset
        #100;
        rst = 0;

        //-------------------------------------------------
        // First Transmission : A5
        //-------------------------------------------------
        #100;

        tx_data = 8'hA5;
        tx_st   = 1;

        #20;
        tx_st   = 0;

        // Wait enough time for one UART frame
        #120000;

        $display("--------------------------------");
        $display("Time = %0t", $time);
        $display("Transmitted = %h", 8'hA5);
        $display("Received    = %h", rx_data);

        //-------------------------------------------------
        // Second Transmission : 3C
        //-------------------------------------------------
        tx_data = 8'h3C;
        tx_st   = 1;

        #20;
        tx_st   = 0;

        // Wait enough time for second frame
        #120000;

        $display("--------------------------------");
        $display("Time = %0t", $time);
        $display("Transmitted = %h", 8'h3C);
        $display("Received    = %h", rx_data);

        //-------------------------------------------------
        // Finish
        //-------------------------------------------------
        #1000;

        $display("--------------------------------");
        $display("UART Simulation Completed");
        $display("--------------------------------");

        $finish;

    end

endmodule

05_UART_Tx_Rx/uart.vcd
$date
	Sun Jul 26 11:52:02 2026
$end
$version
	Icarus Verilog
$end
$timescale
	1ps
$end
$scope module UART_tb $end
$var wire 1 ! tx_serial $end
$var wire 1 " tx_busy $end
$var wire 8 # rx_data [7:0] $end
$var wire 1 $ done $end
$var reg 1 % clk $end
$var reg 1 & rst $end
$var reg 8 ' tx_data [7:0] $end
$var reg 1 ( tx_st $end
$scope module uut_rx $end
$var wire 1 % clk $end
$var wire 1 & rst $end
$var wire 1 ! rx_serial $end
$var reg 3 ) bit_count [2:0] $end
$var reg 16 * count [15:0] $end
$var reg 1 $ done $end
$var reg 8 + rx_data [7:0] $end
$var reg 8 , rx_reg [7:0] $end
$var reg 2 - state [1:0] $end
$upscope $end
$scope module uut_tx $end
$var wire 1 % clk $end
$var wire 1 & rst $end
$var wire 1 " tx_busy $end
$var wire 8 . tx_data [7:0] $end
$var wire 1 ( tx_st $end
$var wire 1 ! tx_serial $end
$var reg 3 / bit_count [2:0] $end
$var reg 16 0 count [15:0] $end
$var reg 2 1 state [1:0] $end
$var reg 8 2 tx_reg [7:0] $end
$upscope $end
$upscope $end
$enddefinitions $end
#0
$dumpvars
b0 2
b0 1
b0 0
b0 /
b0 .
b0 -
b0 ,
b0 +
bx *
bx )
0(
b0 '
1&
0%
0$
b0 #
0"
1!
$end
#10000
1%
#20000
0%
#30000
1%
#40000
0%
#50000
1%
#60000
0%
#70000
1%
#80000
0%
#90000
1%
#100000
0%
0&
#110000
b0 )
b0 *
1%
#120000
0%
#130000
1%
#140000
0%
#150000
1%
#160000
0%
#170000
1%
#180000
0%
#190000
1%
#200000
0%
1(
b10100101 '
b10100101 .
#210000
1"
0!
b1 1
1%
#220000
0%
0(
#230000
b1 0
b10100101 2
b1 -
1%
#240000
0%
#250000
b1 *
b10 0
1%
#260000
0%
#270000
b11 0
b10 *
1%
#280000
0%
#290000
b11 *
b100 0
1%
#300000
0%
#310000
b101 0
b100 *
1%
#320000
0%
#330000
b101 *
b110 0
1%
#340000
0%
#350000
b111 0
b110 *
1%
#360000
0%
#370000
b111 *
b1000 0
1%
#380000
0%
#390000
b1001 0
b1000 *
1%
#400000
0%
#410000
b1001 *
b1010 0
1%
#420000
0%
#430000
b1011 0
b1010 *
1%
#440000
0%
#450000
b1011 *
b1100 0
1%
#460000
0%
#470000
b1101 0
b1100 *
1%
#480000
0%
#490000
b1101 *
b1110 0
1%
#500000
0%
#510000
b1111 0
b1110 *
1%
#520000
0%
#530000
b1111 *
b10000 0
1%
#540000
0%
#550000
b10001 0
b10000 *
1%
#560000
0%
#570000
b10001 *
b10010 0
1%
#580000
0%
#590000
b10011 0
b10010 *
1%
#600000
0%
#610000
b10011 *
b10100 0
1%
#620000
0%
#630000
b10101 0
b10100 *
1%
#640000
0%
#650000
b10101 *
b10110 0
1%
#660000
0%
#670000
b10111 0
b10110 *
1%
#680000
0%
#690000
b10111 *
b11000 0
1%
#700000
0%
#710000
b11001 0
b11000 *
1%
#720000
0%
#730000
b11001 *
b11010 0
1%
#740000
0%
#750000
b11011 0
b11010 *
1%
#760000
0%
#770000
b11011 *
b11100 0
1%
#780000
0%
#790000
b11101 0
b11100 *
1%
#800000
0%
#810000
b11101 *
b11110 0
1%
#820000
0%
#830000
b11111 0
b11110 *
1%
#840000
0%
#850000
b11111 *
b100000 0
1%
#860000
0%
#870000
b100001 0
b100000 *
1%
#880000
0%
#890000
b100001 *
b100010 0
1%
#900000
0%
#910000
b100011 0
b100010 *
1%
#920000
0%
#930000
b100011 *
b100100 0
1%
#940000
0%
#950000
b100101 0
b100100 *
1%
#960000
0%
#970000
b100101 *
b100110 0
1%
#980000
0%
#990000
b100111 0
b100110 *
1%
#1000000
0%
#1010000
b100111 *
b101000 0
1%
#1020000
0%
#1030000
b101001 0
b101000 *
1%
#1040000
0%
#1050000
b101001 *
b101010 0
1%
#1060000
0%
#1070000
b101011 0
b101010 *
1%
#1080000
0%
#1090000
b101011 *
b101100 0
1%
#1100000
0%
#1110000
b101101 0
b101100 *
1%
#1120000
0%
#1130000
b101101 *
b101110 0
1%
#1140000
0%
#1150000
b101111 0
b101110 *
1%
#1160000
0%
#1170000
b101111 *
b110000 0
1%
#1180000
0%
#1190000
b110001 0
b110000 *
1%
#1200000
0%
#1210000
b110001 *
b110010 0
1%
#1220000
0%
#1230000
b110011 0
b110010 *
1%
#1240000
0%
#1250000
b110011 *
b110100 0
1%
#1260000
0%
#1270000
b110101 0
b110100 *
1%
#1280000
0%
#1290000
b110101 *
b110110 0
1%
#1300000
0%
#1310000
b110111 0
b110110 *
1%
#1320000
0%
#1330000
b110111 *
b111000 0
1%
#1340000
0%
#1350000
b111001 0
b111000 *
1%
#1360000
0%
#1370000
b111001 *
b111010 0
1%
#1380000
0%
#1390000
b111011 0
b111010 *
1%
#1400000
0%
#1410000
b111011 *
b111100 0
1%
#1420000
0%
#1430000
b111101 0
b111100 *
1%
#1440000
0%
#1450000
b111101 *
b111110 0
1%
#1460000
0%
#1470000
b111111 0
b111110 *
1%
#1480000
0%
#1490000
b111111 *
b1000000 0
1%
#1500000
0%
#1510000
b1000001 0
b1000000 *
1%
#1520000
0%
#1530000
b1000001 *
b1000010 0
1%
#1540000
0%
#1550000
b1000011 0
b1000010 *
1%
#1560000
0%
#1570000
b1000011 *
b1000100 0
1%
#1580000
0%
#1590000
b1000101 0
b1000100 *
1%
#1600000
0%
#1610000
b1000101 *
b1000110 0
1%
#1620000
0%
#1630000
b1000111 0
b1000110 *
1%
#1640000
0%
#1650000
b1000111 *
b1001000 0
1%
#1660000
0%
#1670000
b1001001 0
b1001000 *
1%
#1680000
0%
#1690000
b1001001 *
b1001010 0
1%
#1700000
0%
#1710000
b1001011 0
b1001010 *
1%
#1720000
0%
#1730000
b1001011 *
b1001100 0
1%
#1740000
0%
#1750000
b1001101 0
b1001100 *
1%
#1760000
0%
#1770000
b1001101 *
b1001110 0
1%
#1780000
0%
#1790000
b1001111 0
b1001110 *
1%
#1800000
0%
#1810000
b1001111 *
b1010000 0
1%
#1820000
0%
#1830000
b1010001 0
b1010000 *
1%
#1840000
0%
#1850000
b1010001 *
b1010010 0
1%
#1860000
0%
#1870000
b1010011 0
b1010010 *
1%
#1880000
0%
#1890000
b1010011 *
b1010100 0
1%
#1900000
0%
#1910000
b1010101 0
b1010100 *
1%
#1920000
0%
#1930000
b1010101 *
b1010110 0
1%
#1940000
0%
#1950000
b1010111 0
b1010110 *
1%
#1960000
0%
#1970000
b1010111 *
b1011000 0
1%
#1980000
0%
#1990000
b1011001 0
b1011000 *
1%
#2000000
0%
#2010000
b1011001 *
b1011010 0
1%
#2020000
0%
#2030000
b1011011 0
b1011010 *
1%
#2040000
0%
#2050000
b1011011 *
b1011100 0
1%
#2060000
0%
#2070000
b1011101 0
b1011100 *
1%
#2080000
0%
#2090000
b1011101 *
b1011110 0
1%
#2100000
0%
#2110000
b1011111 0
b1011110 *
1%
#2120000
0%
#2130000
b1011111 *
b1100000 0
1%
#2140000
0%
#2150000
b1100001 0
b1100000 *
1%
#2160000
0%
#2170000
b1100001 *
b1100010 0
1%
#2180000
0%
#2190000
b1100011 0
b1100010 *
1%
#2200000
0%
#2210000
b1100011 *
b1100100 0
1%
#2220000
0%
#2230000
b1100101 0
b1100100 *
1%
#2240000
0%
#2250000
b1100101 *
b1100110 0
1%
#2260000
0%
#2270000
b1100111 0
b1100110 *
1%
#2280000
0%
#2290000
b1100111 *
b1101000 0
1%
#2300000
0%
#2310000
b1101001 0
b1101000 *
1%
#2320000
0%
#2330000
b1101001 *
b1101010 0
1%
#2340000
0%
#2350000
b1101011 0
b1101010 *
1%
#2360000
0%
#2370000
b1101011 *
b1101100 0
1%
#2380000
0%
#2390000
b1101101 0
b1101100 *
1%
#2400000
0%
#2410000
b1101101 *
b1101110 0
1%
#2420000
0%
#2430000
b1101111 0
b1101110 *
1%
#2440000
0%
#2450000
b1101111 *
b1110000 0
1%
#2460000
0%
#2470000
b1110001 0
b1110000 *
1%
#2480000
0%
#2490000
b1110001 *
b1110010 0
1%
#2500000
0%
#2510000
b1110011 0
b1110010 *
1%
#2520000
0%
#2530000
b1110011 *
b1110100 0
1%
#2540000
0%
#2550000
b1110101 0
b1110100 *
1%
#2560000
0%
#2570000
b1110101 *
b1110110 0
1%
#2580000
0%
#2590000
b1110111 0
b1110110 *
1%
#2600000
0%
#2610000
b1110111 *
b1111000 0
1%
#2620000
0%
#2630000
b1111001 0
b1111000 *
1%
#2640000
0%
#2650000
b1111001 *
b1111010 0
1%
#2660000
0%
#2670000
b1111011 0
b1111010 *
1%
#2680000
0%
#2690000
b1111011 *
b1111100 0
1%
#2700000
0%
#2710000
b1111101 0
b1111100 *
1%
#2720000
0%
#2730000
b1111101 *
b1111110 0
1%
#2740000
0%
#2750000
b1111111 0
b1111110 *
1%
#2760000
0%
#2770000
b1111111 *
b10000000 0
1%
#2780000
0%
#2790000
b10000001 0
b10000000 *
1%
#2800000
0%
#2810000
b10000001 *
b10000010 0
1%
#2820000
0%
#2830000
b10000011 0
b10000010 *
1%
#2840000
0%
#2850000
b10000011 *
b10000100 0
1%
#2860000
0%
#2870000
b10000101 0
b10000100 *
1%
#2880000
0%
#2890000
b10000101 *
b10000110 0
1%
#2900000
0%
#2910000
b10000111 0
b10000110 *
1%
#2920000
0%
#2930000
b10000111 *
b10001000 0
1%
#2940000
0%
#2950000
b10001001 0
b10001000 *
1%
#2960000
0%
#2970000
b10001001 *
b10001010 0
1%
#2980000
0%
#2990000
b10001011 0
b10001010 *
1%
#3000000
0%
#3010000
b10001011 *
b10001100 0
1%
#3020000
0%
#3030000
b10001101 0
b10001100 *
1%
#3040000
0%
#3050000
b10001101 *
b10001110 0
1%
#3060000
0%
#3070000
b10001111 0
b10001110 *
1%
#3080000
0%
#3090000
b10001111 *
b10010000 0
1%
#3100000
0%
#3110000
b10010001 0
b10010000 *
1%
#3120000
0%
#3130000
b10010001 *
b10010010 0
1%
#3140000
0%
#3150000
b10010011 0
b10010010 *
1%
#3160000
0%
#3170000
b10010011 *
b10010100 0
1%
#3180000
0%
#3190000
b10010101 0
b10010100 *
1%
#3200000
0%
#3210000
b10010101 *
b10010110 0
1%
#3220000
0%
#3230000
b10010111 0
b10010110 *
1%
#3240000
0%
#3250000
b10010111 *
b10011000 0
1%
#3260000
0%
#3270000
b10011001 0
b10011000 *
1%
#3280000
0%
#3290000
b10011001 *
b10011010 0
1%
#3300000
0%
#3310000
b10011011 0
b10011010 *
1%
#3320000
0%
#3330000
b10011011 *
b10011100 0
1%
#3340000
0%
#3350000
b10011101 0
b10011100 *
1%
#3360000
0%
#3370000
b10011101 *
b10011110 0
1%
#3380000
0%
#3390000
b10011111 0
b10011110 *
1%
#3400000
0%
#3410000
b10011111 *
b10100000 0
1%
#3420000
0%
#3430000
b10100001 0
b10100000 *
1%
#3440000
0%
#3450000
b10100001 *
b10100010 0
1%
#3460000
0%
#3470000
b10100011 0
b10100010 *
1%
#3480000
0%
#3490000
b10100011 *
b10100100 0
1%
#3500000
0%
#3510000
b10100101 0
b10100100 *
1%
#3520000
0%
#3530000
b10100101 *
b10100110 0
1%
#3540000
0%
#3550000
b10100111 0
b10100110 *
1%
#3560000
0%
#3570000
b10100111 *
b10101000 0
1%
#3580000
0%
#3590000
b10101001 0
b10101000 *
1%
#3600000
0%
#3610000
b10101001 *
b10101010 0
1%
#3620000
0%
#3630000
b10101011 0
b10101010 *
1%
#3640000
0%
#3650000
b10101011 *
b10101100 0
1%
#3660000
0%
#3670000
b10101101 0
b10101100 *
1%
#3680000
0%
#3690000
b10101101 *
b10101110 0
1%
#3700000
0%
#3710000
b10101111 0
b10101110 *
1%
#3720000
0%
#3730000
b10101111 *
b10110000 0
1%
#3740000
0%
#3750000
b10110001 0
b10110000 *
1%
#3760000
0%
#3770000
b10110001 *
b10110010 0
1%
#3780000
0%
#3790000
b10110011 0
b10110010 *
1%
#3800000
0%
#3810000
b10110011 *
b10110100 0
1%
#3820000
0%
#3830000
b10110101 0
b10110100 *
1%
#3840000
0%
#3850000
b10110101 *
b10110110 0
1%
#3860000
0%
#3870000
b10110111 0
b10110110 *
1%
#3880000
0%
#3890000
b10110111 *
b10111000 0
1%
#3900000
0%
#3910000
b10111001 0
b10111000 *
1%
#3920000
0%
#3930000
b10111001 *
b10111010 0
1%
#3940000
0%
#3950000
b10111011 0
b10111010 *
1%
#3960000
0%
#3970000
b10111011 *
b10111100 0
1%
#3980000
0%
#3990000
b10111101 0
b10111100 *
1%
#4000000
0%
#4010000
b10111101 *
b10111110 0
1%
#4020000
0%
#4030000
b10111111 0
b10111110 *
1%
#4040000
0%
#4050000
b10111111 *
b11000000 0
1%
#4060000
0%
#4070000
b11000001 0
b11000000 *
1%
#4080000
0%
#4090000
b11000001 *
b11000010 0
1%
#4100000
0%
#4110000
b11000011 0
b11000010 *
1%
#4120000
0%
#4130000
b11000011 *
b11000100 0
1%
#4140000
0%
#4150000
b11000101 0
b11000100 *
1%
#4160000
0%
#4170000
b11000101 *
b11000110 0
1%
#4180000
0%
#4190000
b11000111 0
b11000110 *
1%
#4200000
0%
#4210000
b11000111 *
b11001000 0
1%
#4220000
0%
#4230000
b11001001 0
b11001000 *
1%
#4240000
0%
#4250000
b11001001 *
b11001010 0
1%
#4260000
0%
#4270000
b11001011 0
b11001010 *
1%
#4280000
0%
#4290000
b11001011 *
b11001100 0
1%
#4300000
0%
#4310000
b11001101 0
b11001100 *
1%
#4320000
0%
#4330000
b11001101 *
b11001110 0
1%
#4340000
0%
#4350000
b11001111 0
b11001110 *
1%
#4360000
0%
#4370000
b11001111 *
b11010000 0
1%
#4380000
0%
#4390000
b11010001 0
b11010000 *
1%
#4400000
0%
#4410000
b11010001 *
b11010010 0
1%
#4420000
0%
#4430000
b11010011 0
b11010010 *
1%
#4440000
0%
#4450000
b11010011 *
b11010100 0
1%
#4460000
0%
#4470000
b11010101 0
b11010100 *
1%
#4480000
0%
#4490000
b11010101 *
b11010110 0
1%
#4500000
0%
#4510000
b11010111 0
b0 *
b10 -
1%
#4520000
0%
#4530000
b1 *
b11011000 0
1%
#4540000
0%
#4550000
b11011001 0
b10 *
1%
#4560000
0%
#4570000
b11 *
b11011010 0
1%
#4580000
0%
#4590000
b11011011 0
b100 *
1%
#4600000
0%
#4610000
b101 *
b11011100 0
1%
#4620000
0%
#4630000
b11011101 0
b110 *
1%
#4640000
0%
#4650000
b111 *
b11011110 0
1%
#4660000
0%
#4670000
b11011111 0
b1000 *
1%
#4680000
0%
#4690000
b1001 *
b11100000 0
1%
#4700000
0%
#4710000
b11100001 0
b1010 *
1%
#4720000
0%
#4730000
b1011 *
b11100010 0
1%
#4740000
0%
#4750000
b11100011 0
b1100 *
1%
#4760000
0%
#4770000
b1101 *
b11100100 0
1%
#4780000
0%
#4790000
b11100101 0
b1110 *
1%
#4800000
0%
#4810000
b1111 *
b11100110 0
1%
#4820000
0%
#4830000
b11100111 0
b10000 *
1%
#4840000
0%
#4850000
b10001 *
b11101000 0
1%
#4860000
0%
#4870000
b11101001 0
b10010 *
1%
#4880000
0%
#4890000
b10011 *
b11101010 0
1%
#4900000
0%
#4910000
b11101011 0
b10100 *
1%
#4920000
0%
#4930000
b10101 *
b11101100 0
1%
#4940000
0%
#4950000
b11101101 0
b10110 *
1%
#4960000
0%
#4970000
b10111 *
b11101110 0
1%
#4980000
0%
#4990000
b11101111 0
b11000 *
1%
#5000000
0%
#5010000
b11001 *
b11110000 0
1%
#5020000
0%
#5030000
b11110001 0
b11010 *
1%
#5040000
0%
#5050000
b11011 *
b11110010 0
1%
#5060000
0%
#5070000
b11110011 0
b11100 *
1%
#5080000
0%
#5090000
b11101 *
b11110100 0
1%
#5100000
0%
#5110000
b11110101 0
b11110 *
1%
#5120000
0%
#5130000
b11111 *
b11110110 0
1%
#5140000
0%
#5150000
b11110111 0
b100000 *
1%
#5160000
0%
#5170000
b100001 *
b11111000 0
1%
#5180000
0%
#5190000
b11111001 0
b100010 *
1%
#5200000
0%
#5210000
b100011 *
b11111010 0
1%
#5220000
0%
#5230000
b11111011 0
b100100 *
1%
#5240000
0%
#5250000
b100101 *
b11111100 0
1%
#5260000
0%
#5270000
b11111101 0
b100110 *
1%
#5280000
0%
#5290000
b100111 *
b11111110 0
1%
#5300000
0%
#5310000
b11111111 0
b101000 *
1%
#5320000
0%
#5330000
b101001 *
b100000000 0
1%
#5340000
0%
#5350000
b100000001 0
b101010 *
1%
#5360000
0%
#5370000
b101011 *
b100000010 0
1%
#5380000
0%
#5390000
b100000011 0
b101100 *
1%
#5400000
0%
#5410000
b101101 *
b100000100 0
1%
#5420000
0%
#5430000
b100000101 0
b101110 *
1%
#5440000
0%
#5450000
b101111 *
b100000110 0
1%
#5460000
0%
#5470000
b100000111 0
b110000 *
1%
#5480000
0%
#5490000
b110001 *
b100001000 0
1%
#5500000
0%
#5510000
b100001001 0
b110010 *
1%
#5520000
0%
#5530000
b110011 *
b100001010 0
1%
#5540000
0%
#5550000
b100001011 0
b110100 *
1%
#5560000
0%
#5570000
b110101 *
b100001100 0
1%
#5580000
0%
#5590000
b100001101 0
b110110 *
1%
#5600000
0%
#5610000
b110111 *
b100001110 0
1%
#5620000
0%
#5630000
b100001111 0
b111000 *
1%
#5640000
0%
#5650000
b111001 *
b100010000 0
1%
#5660000
0%
#5670000
b100010001 0
b111010 *
1%
#5680000
0%
#5690000
b111011 *
b100010010 0
1%
#5700000
0%
#5710000
b100010011 0
b111100 *
1%
#5720000
0%
#5730000
b111101 *
b100010100 0
1%
#5740000
0%
#5750000
b100010101 0
b111110 *
1%
#5760000
0%
#5770000
b111111 *
b100010110 0
1%
#5780000
0%
#5790000
b100010111 0
b1000000 *
1%
#5800000
0%
#5810000
b1000001 *
b100011000 0
1%
#5820000
0%
#5830000
b100011001 0
b1000010 *
1%
#5840000
0%
#5850000
b1000011 *
b100011010 0
1%
#5860000
0%
#5870000
b100011011 0
b1000100 *
1%
#5880000
0%
#5890000
b1000101 *
b100011100 0
1%
#5900000
0%
#5910000
b100011101 0
b1000110 *
1%
#5920000
0%
#5930000
b1000111 *
b100011110 0
1%
#5940000
0%
#5950000
b100011111 0
b1001000 *
1%
#5960000
0%
#5970000
b1001001 *
b100100000 0
1%
#5980000
0%
#5990000
b100100001 0
b1001010 *
1%
#6000000
0%
#6010000
b1001011 *
b100100010 0
1%
#6020000
0%
#6030000
b100100011 0
b1001100 *
1%
#6040000
0%
#6050000
b1001101 *
b100100100 0
1%
#6060000
0%
#6070000
b100100101 0
b1001110 *
1%
#6080000
0%
#6090000
b1001111 *
b100100110 0
1%
#6100000
0%
#6110000
b100100111 0
b1010000 *
1%
#6120000
0%
#6130000
b1010001 *
b100101000 0
1%
#6140000
0%
#6150000
b100101001 0
b1010010 *
1%
#6160000
0%
#6170000
b1010011 *
b100101010 0
1%
#6180000
0%
#6190000
b100101011 0
b1010100 *
1%
#6200000
0%
#6210000
b1010101 *
b100101100 0
1%
#6220000
0%
#6230000
b100101101 0
b1010110 *
1%
#6240000
0%
#6250000
b1010111 *
b100101110 0
1%
#6260000
0%
#6270000
b100101111 0
b1011000 *
1%
#6280000
0%
#6290000
b1011001 *
b100110000 0
1%
#6300000
0%
#6310000
b100110001 0
b1011010 *
1%
#6320000
0%
#6330000
b1011011 *
b100110010 0
1%
#6340000
0%
#6350000
b100110011 0
b1011100 *
1%
#6360000
0%
#6370000
b1011101 *
b100110100 0
1%
#6380000
0%
#6390000
b100110101 0
b1011110 *
1%
#6400000
0%
#6410000
b1011111 *
b100110110 0
1%
#6420000
0%
#6430000
b100110111 0
b1100000 *
1%
#6440000
0%
#6450000
b1100001 *
b100111000 0
1%
#6460000
0%
#6470000
b100111001 0
b1100010 *
1%
#6480000
0%
#6490000
b1100011 *
b100111010 0
1%
#6500000
0%
#6510000
b100111011 0
b1100100 *
1%
#6520000
0%
#6530000
b1100101 *
b100111100 0
1%
#6540000
0%
#6550000
b100111101 0
b1100110 *
1%
#6560000
0%
#6570000
b1100111 *
b100111110 0
1%
#6580000
0%
#6590000
b100111111 0
b1101000 *
1%
#6600000
0%
#6610000
b1101001 *
b101000000 0
1%
#6620000
0%
#6630000
b101000001 0
b1101010 *
1%
#6640000
0%
#6650000
b1101011 *
b101000010 0
1%
#6660000
0%
#6670000
b101000011 0
b1101100 *
1%
#6680000
0%
#6690000
b1101101 *
b101000100 0
1%
#6700000
0%
#6710000
b101000101 0
b1101110 *
1%
#6720000
0%
#6730000
b1101111 *
b101000110 0
1%
#6740000
0%
#6750000
b101000111 0
b1110000 *
1%
#6760000
0%
#6770000
b1110001 *
b101001000 0
1%
#6780000
0%
#6790000
b101001001 0
b1110010 *
1%
#6800000
0%
#6810000
b1110011 *
b101001010 0
1%
#6820000
0%
#6830000
b101001011 0
b1110100 *
1%
#6840000
0%
#6850000
b1110101 *
b101001100 0
1%
#6860000
0%
#6870000
b101001101 0
b1110110 *
1%
#6880000
0%
#6890000
b1110111 *
b101001110 0
1%
#6900000
0%
#6910000
b101001111 0
b1111000 *
1%
#6920000
0%
#6930000
b1111001 *
b101010000 0
1%
#6940000
0%
#6950000
b101010001 0
b1111010 *
1%
#6960000
0%
#6970000
b1111011 *
b101010010 0
1%
#6980000
0%
#6990000
b101010011 0
b1111100 *
1%
#7000000
0%
#7010000
b1111101 *
b101010100 0
1%
#7020000
0%
#7030000
b101010101 0
b1111110 *
1%
#7040000
0%
#7050000
b1111111 *
b101010110 0
1%
#7060000
0%
#7070000
b101010111 0
b10000000 *
1%
#7080000
0%
#7090000
b10000001 *
b101011000 0
1%
#7100000
0%
#7110000
b101011001 0
b10000010 *
1%
#7120000
0%
#7130000
b10000011 *
b101011010 0
1%
#7140000
0%
#7150000
b101011011 0
b10000100 *
1%
#7160000
0%
#7170000
b10000101 *
b101011100 0
1%
#7180000
0%
#7190000
b101011101 0
b10000110 *
1%
#7200000
0%
#7210000
b10000111 *
b101011110 0
1%
#7220000
0%
#7230000
b101011111 0
b10001000 *
1%
#7240000
0%
#7250000
b10001001 *
b101100000 0
1%
#7260000
0%
#7270000
b101100001 0
b10001010 *
1%
#7280000
0%
#7290000
b10001011 *
b101100010 0
1%
#7300000
0%
#7310000
b101100011 0
b10001100 *
1%
#7320000
0%
#7330000
b10001101 *
b101100100 0
1%
#7340000
0%
#7350000
b101100101 0
b10001110 *
1%
#7360000
0%
#7370000
b10001111 *
b101100110 0
1%
#7380000
0%
#7390000
b101100111 0
b10010000 *
1%
#7400000
0%
#7410000
b10010001 *
b101101000 0
1%
#7420000
0%
#7430000
b101101001 0
b10010010 *
1%
#7440000
0%
#7450000
b10010011 *
b101101010 0
1%
#7460000
0%
#7470000
b101101011 0
b10010100 *
1%
#7480000
0%
#7490000
b10010101 *
b101101100 0
1%
#7500000
0%
#7510000
b101101101 0
b10010110 *
1%
#7520000
0%
#7530000
b10010111 *
b101101110 0
1%
#7540000
0%
#7550000
b101101111 0
b10011000 *
1%
#7560000
0%
#7570000
b10011001 *
b101110000 0
1%
#7580000
0%
#7590000
b101110001 0
b10011010 *
1%
#7600000
0%
#7610000
b10011011 *
b101110010 0
1%
#7620000
0%
#7630000
b101110011 0
b10011100 *
1%
#7640000
0%
#7650000
b10011101 *
b101110100 0
1%
#7660000
0%
#7670000
b101110101 0
b10011110 *
1%
#7680000
0%
#7690000
b10011111 *
b101110110 0
1%
#7700000
0%
#7710000
b101110111 0
b10100000 *
1%
#7720000
0%
#7730000
b10100001 *
b101111000 0
1%
#7740000
0%
#7750000
b101111001 0
b10100010 *
1%
#7760000
0%
#7770000
b10100011 *
b101111010 0
1%
#7780000
0%
#7790000
b101111011 0
b10100100 *
1%
#7800000
0%
#7810000
b10100101 *
b101111100 0
1%
#7820000
0%
#7830000
b101111101 0
b10100110 *
1%
#7840000
0%
#7850000
b10100111 *
b101111110 0
1%
#7860000
0%
#7870000
b101111111 0
b10101000 *
1%
#7880000
0%
#7890000
b10101001 *
b110000000 0
1%
#7900000
0%
#7910000
b110000001 0
b10101010 *
1%
#7920000
0%
#7930000
b10101011 *
b110000010 0
1%
#7940000
0%
#7950000
b110000011 0
b10101100 *
1%
#7960000
0%
#7970000
b10101101 *
b110000100 0
1%
#7980000
0%
#7990000
b110000101 0
b10101110 *
1%
#8000000
0%
#8010000
b10101111 *
b110000110 0
1%
#8020000
0%
#8030000
b110000111 0
b10110000 *
1%
#8040000
0%
#8050000
b10110001 *
b110001000 0
1%
#8060000
0%
#8070000
b110001001 0
b10110010 *
1%
#8080000
0%
#8090000
b10110011 *
b110001010 0
1%
#8100000
0%
#8110000
b110001011 0
b10110100 *
1%
#8120000
0%
#8130000
b10110101 *
b110001100 0
1%
#8140000
0%
#8150000
b110001101 0
b10110110 *
1%
#8160000
0%
#8170000
b10110111 *
b110001110 0
1%
#8180000
0%
#8190000
b110001111 0
b10111000 *
1%
#8200000
0%
#8210000
b10111001 *
b110010000 0
1%
#8220000
0%
