04_MIPS32_Single_Cycle/MIPS_SingleCycle.v
module ProgramCounter(

    input wire clk,
    input wire reset,              // Active-high synchronous reset
    input wire [31:0] next_pc,     // Next PC value
    output reg [31:0] pc           // Current PC
);

always @(posedge clk)
begin
    if (reset)
        pc <= 32'd0;
    else
        pc <= next_pc;
end

endmodule


module InstructionMem(

    input  wire [31:0] address,
    output reg  [31:0] instruction

);

    // 1024 × 32-bit instruction memory
    reg [31:0] instrmem [0:1023];

    initial
    begin
        $readmemh("instr.mem", instrmem);
    end

    always @(*)
    begin
        // Convert byte address to word address
        instruction = instrmem[address[11:2]];
    end

endmodule


module RegisterFile(

    input wire clk,
    input wire rst,

    input wire RegWrite,

    input wire [4:0] Rs,
    input wire [4:0] Rt,
    input wire [4:0] Rd,

    input wire [31:0] WriteData,

    output wire [31:0] ReadDataA,
    output wire [31:0] ReadDataB

);

    // Register File (32 × 32)
    reg [31:0] Register [0:31];
    integer i;

    // Initialize Registers
    initial begin
        for(i = 0; i < 32; i = i + 1)
            Register[i] = 32'd0;
    end

    // Asynchronous Read
    assign ReadDataA = (Rs == 5'd0) ? 32'd0 : Register[Rs];
    assign ReadDataB = (Rt == 5'd0) ? 32'd0 : Register[Rt];

    // Synchronous Write
    always @(posedge clk) begin
        if(rst) begin
            for(i = 0; i < 32; i = i + 1)
                Register[i] <= 32'd0;
        end
        else if(RegWrite && (Rd != 5'd0))
            Register[Rd] <= WriteData;
    end

endmodule


module SignExtend(

    input wire [15:0] imm,
    output wire [31:0] sign_ext_imm

);

    // Sign Extend 16-bit Immediate to 32-bit
    assign sign_ext_imm = {{16{imm[15]}}, imm};

endmodule


module ZeroExtend(

    input wire [15:0] imm,
    output wire [31:0] zero_ext_imm

);

    // Zero Extend 16-bit Immediate to 32-bit
    assign zero_ext_imm = {16'b0, imm};

endmodule


module ALU(

    input wire [31:0] OperandA,
    input wire [31:0] OperandB,
    input wire [3:0] alu_control,

    output reg [31:0] result,
    output wire zero

);

    // ALU Operations
    always @(*) begin
        case (alu_control)

            4'b0000: result = OperandA & OperandB;                                  // AND
            4'b0001: result = OperandA | OperandB;                                  // OR
            4'b0010: result = OperandA + OperandB;                                  // ADD
            4'b0011: result = OperandA ^ OperandB;                                  // XOR
            4'b0100: result = OperandA << OperandB[4:0];                                 // SLL
            4'b0101: result = OperandA >> OperandB[4:0];                                 // SRL
            4'b0110: result = OperandA - OperandB;                                  // SUB
            4'b0111: result = ($signed(OperandA) < $signed(OperandB)) ? 32'd1 : 32'd0; // SLT
            4'b1000: result = $signed(OperandA) >>> OperandB[4:0];                       // SRA
            4'b1001: result = OperandB << 16;                                       // LUI
            4'b1010: result = OperandA | OperandB;   // ORI
            4'b1100: result = ~(OperandA | OperandB);   // NOR                               

            default: result = 32'd0;

        endcase
    end

    // Zero Flag
    assign zero = (result == 32'd0);

endmodule


module ControlUnit(

    input wire [5:0] opcode,

    output reg RegDst,
    output reg ALUSrc,
    output reg MemtoReg,
    output reg RegWrite,
    output reg MemRead,
    output reg MemWrite,
    output reg Branch,
    output reg [2:0] ALUOp

);

    always @(*) begin

        case(opcode)

            // R-Type
            6'b000000: begin
                RegDst   = 1'b1;
                ALUSrc   = 1'b0;
                MemtoReg = 1'b0;
                RegWrite = 1'b1;
                MemRead  = 1'b0;
                MemWrite = 1'b0;
                Branch   = 1'b0;
                ALUOp    = 3'b010;
            end

            // LW
            6'b100011: begin
                RegDst   = 1'b0;
                ALUSrc   = 1'b1;
                MemtoReg = 1'b1;
                RegWrite = 1'b1;
                MemRead  = 1'b1;
                MemWrite = 1'b0;
                Branch   = 1'b0;
                ALUOp    = 3'b000;
            end

            // SW
            6'b101011: begin
                RegDst   = 1'b0;
                ALUSrc   = 1'b1;
                MemtoReg = 1'b0;
                RegWrite = 1'b0;
                MemRead  = 1'b0;
                MemWrite = 1'b1;
                Branch   = 1'b0;
                ALUOp    = 3'b000;
            end

            // BEQ
            6'b000100: begin
                RegDst   = 1'b0;
                ALUSrc   = 1'b0;
                MemtoReg = 1'b0;
                RegWrite = 1'b0;
                MemRead  = 1'b0;
                MemWrite = 1'b0;
                Branch   = 1'b1;
                ALUOp    = 3'b001;
            end

            // ADDI
            6'b001000: begin
                RegDst   = 1'b0;
                ALUSrc   = 1'b1;
                MemtoReg = 1'b0;
                RegWrite = 1'b1;
                MemRead  = 1'b0;
                MemWrite = 1'b0;
                Branch   = 1'b0;
                ALUOp    = 3'b000;
            end

            // LUI
            6'b001111: begin
                RegDst   = 1'b0;
                ALUSrc   = 1'b1;
                MemtoReg = 1'b0;
                RegWrite = 1'b1;
                MemRead  = 1'b0;
                MemWrite = 1'b0;
                Branch   = 1'b0;
                ALUOp    = 3'b011;
            end

            // ORI
            6'b001101: begin
                RegDst   = 1'b0;
                ALUSrc   = 1'b1;
                MemtoReg = 1'b0;
                RegWrite = 1'b1;
                MemRead  = 1'b0;
                MemWrite = 1'b0;
                Branch   = 1'b0;
                ALUOp    = 3'b100;
            end

            default: begin
                RegDst   = 1'b0;
                ALUSrc   = 1'b0;
                MemtoReg = 1'b0;
                RegWrite = 1'b0;
                MemRead  = 1'b0;
                MemWrite = 1'b0;
                Branch   = 1'b0;
                ALUOp    = 3'b000;
            end

        endcase

    end

endmodule


module ALUControl(

    input wire [2:0] ALUOp,
    input wire [5:0] funct,

    output reg [3:0] alu_control

);

    always @(*) begin

        case(ALUOp)

            // ADD (LW, SW, ADDI)
            3'b000: alu_control = 4'b0010;

            // SUB (BEQ)
            3'b001: alu_control = 4'b0110;

            // R-Type
            3'b010: begin

                case(funct)

                    6'b000000: alu_control = 4'b0100; // SLL
                    6'b000010: alu_control = 4'b0101; // SRL
                    6'b000011: alu_control = 4'b1000; // SRA
                    6'b100000: alu_control = 4'b0010; // ADD
                    6'b100010: alu_control = 4'b0110; // SUB
                    6'b100100: alu_control = 4'b0000; // AND
                    6'b100101: alu_control = 4'b0001; // OR
                    6'b100110: alu_control = 4'b0011; // XOR
                    6'b100111: alu_control = 4'b1100; // NOR
                    6'b101010: alu_control = 4'b0111; // SLT

                    default:   alu_control = 4'b1111;

                endcase

            end

            // LUI
            3'b011: alu_control = 4'b1001;

            // ORI
            3'b100: alu_control = 4'b1010;

            default: alu_control = 4'b1111;

        endcase

    end

endmodule


module DataMemory(

    input wire clk,
    input wire mem_read,
    input wire mem_write,

    input wire [31:0] addr,
    input wire [31:0] write_data,

    output reg [31:0] read_data

);

    // 1024 × 32-bit Data Memory
    reg [31:0] memory [0:1023];

    // Read Operation
    always @(*) begin
        if(mem_read)
            read_data = memory[addr[11:2]];
        else
            read_data = 32'd0;
    end

    // Write Operation
    always @(posedge clk) begin
        if(mem_write)
            memory[addr[11:2]] <= write_data;
    end

endmodule


module Mux2to1 #(parameter WIDTH = 32)(

    input wire [WIDTH-1:0] in0,
    input wire [WIDTH-1:0] in1,
    input wire sel,

    output wire [WIDTH-1:0] out

);

    assign out = sel ? in1 : in0;

endmodule


module MIPS_SingleCycle(

    input wire clk,
    input wire reset,

    output wire halt

);

    // PC Signals
    wire [31:0] pc_current;
    wire [31:0] pc_next;
    wire [31:0] pc_plus4;
    wire [31:0] pc_branch;

    // Instruction
    wire [31:0] instruction;

    // Control Signals
    wire RegDst;
    wire ALUSrc;
    wire MemtoReg;
    wire RegWrite;
    wire MemRead;
    wire MemWrite;
    wire Branch;
    wire [2:0] ALUOp;

    // Register File
    wire [4:0] write_reg_addr;
    wire [31:0] ReadDataA;
    wire [31:0] ReadDataB;
    wire [31:0] WriteBackData;

    // Immediate Extension
    wire [31:0] sign_ext_imm;
    wire [31:0] zero_ext_imm;
    wire [31:0] immediate;

    // ALU
    wire [31:0] OperandA;
    wire [31:0] OperandB;
    wire [31:0] ALUResult;
    wire [3:0] alu_control;
    wire zero;

    // Data Memory
    wire [31:0] ReadData;

    // Branch
    wire branch_taken;

    // Shift Instructions
    wire is_shift_instruction;
    wire [31:0] shamt;

    // Program Counter
    ProgramCounter PC(
        .clk(clk),
        .reset(reset),
        .next_pc(pc_next),
        .pc(pc_current)
    );

    assign pc_plus4 = pc_current + 32'd4;

    // Instruction Memory
    InstructionMem InstructionMemory(
        .address(pc_current),
        .instruction(instruction)
    );

    // Control Unit
    ControlUnit CU(
        .opcode(instruction[31:26]),
        .RegDst(RegDst),
        .ALUSrc(ALUSrc),
        .MemtoReg(MemtoReg),
        .RegWrite(RegWrite),
        .MemRead(MemRead),
        .MemWrite(MemWrite),
        .Branch(Branch),
        .ALUOp(ALUOp)
    );

    // Destination Register MUX
    Mux2to1 #(5) RegDstMux(
        .in0(instruction[20:16]),
        .in1(instruction[15:11]),
        .sel(RegDst),
        .out(write_reg_addr)
    );

    // Register File
    RegisterFile RF(
        .clk(clk),
        .rst(reset),
        .RegWrite(RegWrite),
        .Rs(instruction[25:21]),
        .Rt(instruction[20:16]),
        .Rd(write_reg_addr),
        .WriteData(WriteBackData),
        .ReadDataA(ReadDataA),
        .ReadDataB(ReadDataB)
    );

    // Immediate Extension
    SignExtend SignExt(
        .imm(instruction[15:0]),
        .sign_ext_imm(sign_ext_imm)
    );

    ZeroExtend ZeroExt(
        .imm(instruction[15:0]),
        .zero_ext_imm(zero_ext_imm)
    );

    // ORI uses Zero Extend
    assign immediate =
        (instruction[31:26] == 6'b001101) ?
        zero_ext_imm :
        sign_ext_imm;

    // Shift Instruction Detection
    assign is_shift_instruction =
        (instruction[31:26] == 6'b000000) &&
        (
            (instruction[5:0] == 6'b000000) ||
            (instruction[5:0] == 6'b000010) ||
            (instruction[5:0] == 6'b000011)
        );

    assign shamt = {27'd0, instruction[10:6]};

    // ALU Operand A
    assign OperandA =
        is_shift_instruction ?
        ReadDataB :
        ReadDataA;

    // ALU Operand B
    wire [31:0] ALUSrcIn0;
    
    assign ALUSrcIn0 = is_shift_instruction ? shamt : ReadDataB;

    Mux2to1 #(32) ALUSrcMux(
        .in0(ALUSrcIn0),
        .in1(immediate),
        .sel(ALUSrc),
        .out(OperandB)
    );

    // ALU Control
    ALUControl ALUCtrl(
        .ALUOp(ALUOp),
        .funct(instruction[5:0]),
        .alu_control(alu_control)
    );

        // ALU
    ALU ALUUnit(
        .OperandA(OperandA),
        .OperandB(OperandB),
        .alu_control(alu_control),
        .result(ALUResult),
        .zero(zero)
    );

    // Data Memory
    DataMemory DataMem(
        .clk(clk),
        .mem_read(MemRead),
        .mem_write(MemWrite),
        .addr(ALUResult),
        .write_data(ReadDataB),
        .read_data(ReadData)
    );

    // Write Back MUX
    Mux2to1 #(32) MemtoRegMux(
        .in0(ALUResult),
        .in1(ReadData),
        .sel(MemtoReg),
        .out(WriteBackData)
    );

    // Branch Logic
    assign pc_branch = pc_plus4 + (sign_ext_imm << 2);
    assign branch_taken = Branch & zero;

    // Next PC
    assign pc_next = branch_taken ? pc_branch : pc_plus4;

    // HALT Instruction
    assign halt = (instruction == 32'hFFFFFFFF);

endmodule

04_MIPS32_Single_Cycle/tb_MIPS_SingleCycle.v
`timescale 1ns/1ps

module tb_MIPS_SingleCycle;

    reg clk;
    reg reset;

    wire halt;

    // Instantiate DUT
    MIPS_SingleCycle DUT(
        .clk(clk),
        .reset(reset),
        .halt(halt)
    );

    //-------------------------------------------------------
    // Clock Generation (10 ns period)
    //-------------------------------------------------------
    initial
    begin
        clk = 0;
        forever #5 clk = ~clk;
    end

    //-------------------------------------------------------
    // Reset
    //-------------------------------------------------------
    initial
    begin
        reset = 1;
        #20;
        reset = 0;
    end

    //-------------------------------------------------------
    // VCD Dump
    //-------------------------------------------------------
    initial
    begin
        $dumpfile("dump.vcd");
        $dumpvars(0, tb_MIPS_SingleCycle);
    end

    //-------------------------------------------------------
    // Monitor
    //-------------------------------------------------------
    initial
    begin
        $display("---------------------------------------------------------------");
        $display(" Time\tPC\t\tInstruction\tALUResult\tHalt");
        $display("---------------------------------------------------------------");

        $monitor("%4t\t%h\t%h\t%h\t%b",
                 $time,
                 DUT.pc_current,
                 DUT.instruction,
                 DUT.ALUResult,
                 halt);
    end

    //-------------------------------------------------------
    // Finish Simulation
    //-------------------------------------------------------
    initial
    begin
        wait(halt == 1'b1);

        #20;

        $display("\n================ FINAL REGISTER VALUES ================\n");

        $display("R1  = %h", DUT.RF.Register[1]);
        $display("R2  = %d", DUT.RF.Register[2]);
        $display("R3  = %d", DUT.RF.Register[3]);
        $display("R4  = %d", DUT.RF.Register[4]);
        $display("R5  = %d", DUT.RF.Register[5]);
        $display("R6  = %d", DUT.RF.Register[6]);
        $display("R7  = %d", DUT.RF.Register[7]);
        $display("R8  = %h", DUT.RF.Register[8]);
        $display("R9  = %d", DUT.RF.Register[9]);
        $display("R10 = %d", DUT.RF.Register[10]);
        $display("R11 = %d", DUT.RF.Register[11]);
        $display("R12 = %d", DUT.RF.Register[12]);

        $display("\n================ DATA MEMORY ================\n");

        $display("MEM[0] = %d", DUT.DataMem.memory[0]);

        $display("\nSimulation Completed Successfully.");

        $finish;
    end

    //-------------------------------------------------------
    // Timeout Protection
    //-------------------------------------------------------
    initial
    begin
        #1000;

        $display("\nERROR : Simulation Timed Out!");

        $finish;
    end

endmodule

04_MIPS32_Single_Cycle/dump.vcd
$date
	Fri Jul 24 16:42:34 2026
$end
$version
	Icarus Verilog
$end
$timescale
	1ps
$end
$scope module tb_MIPS_SingleCycle $end
$var wire 1 ! halt $end
$var reg 1 " clk $end
$var reg 1 # reset $end
$scope module DUT $end
$var wire 1 $ branch_taken $end
$var wire 1 " clk $end
$var wire 1 % is_shift_instruction $end
$var wire 1 # reset $end
$var wire 32 & zero_ext_imm [31:0] $end
$var wire 1 ' zero $end
$var wire 5 ( write_reg_addr [4:0] $end
$var wire 32 ) sign_ext_imm [31:0] $end
$var wire 32 * shamt [31:0] $end
$var wire 32 + pc_plus4 [31:0] $end
$var wire 32 , pc_next [31:0] $end
$var wire 32 - pc_current [31:0] $end
$var wire 32 . pc_branch [31:0] $end
$var wire 32 / instruction [31:0] $end
$var wire 32 0 immediate [31:0] $end
$var wire 1 ! halt $end
$var wire 4 1 alu_control [3:0] $end
$var wire 32 2 WriteBackData [31:0] $end
$var wire 1 3 RegWrite $end
$var wire 1 4 RegDst $end
$var wire 32 5 ReadDataB [31:0] $end
$var wire 32 6 ReadDataA [31:0] $end
$var wire 32 7 ReadData [31:0] $end
$var wire 32 8 OperandB [31:0] $end
$var wire 32 9 OperandA [31:0] $end
$var wire 1 : MemtoReg $end
$var wire 1 ; MemWrite $end
$var wire 1 < MemRead $end
$var wire 1 = Branch $end
$var wire 32 > ALUSrcIn0 [31:0] $end
$var wire 1 ? ALUSrc $end
$var wire 32 @ ALUResult [31:0] $end
$var wire 3 A ALUOp [2:0] $end
$scope module ALUCtrl $end
$var wire 6 B funct [5:0] $end
$var wire 3 C ALUOp [2:0] $end
$var reg 4 D alu_control [3:0] $end
$upscope $end
$scope module ALUSrcMux $end
$var wire 32 E in0 [31:0] $end
$var wire 32 F in1 [31:0] $end
$var wire 1 ? sel $end
$var wire 32 G out [31:0] $end
$upscope $end
$scope module ALUUnit $end
$var wire 32 H OperandA [31:0] $end
$var wire 32 I OperandB [31:0] $end
$var wire 4 J alu_control [3:0] $end
$var wire 1 ' zero $end
$var reg 32 K result [31:0] $end
$upscope $end
$scope module CU $end
$var wire 6 L opcode [5:0] $end
$var reg 3 M ALUOp [2:0] $end
$var reg 1 ? ALUSrc $end
$var reg 1 = Branch $end
$var reg 1 < MemRead $end
$var reg 1 ; MemWrite $end
$var reg 1 : MemtoReg $end
$var reg 1 4 RegDst $end
$var reg 1 3 RegWrite $end
$upscope $end
$scope module DataMem $end
$var wire 32 N addr [31:0] $end
$var wire 1 " clk $end
$var wire 1 < mem_read $end
$var wire 1 ; mem_write $end
$var wire 32 O write_data [31:0] $end
$var reg 32 P read_data [31:0] $end
$upscope $end
$scope module InstructionMemory $end
$var wire 32 Q address [31:0] $end
$var reg 32 R instruction [31:0] $end
$upscope $end
$scope module MemtoRegMux $end
$var wire 32 S in0 [31:0] $end
$var wire 32 T in1 [31:0] $end
$var wire 1 : sel $end
$var wire 32 U out [31:0] $end
$upscope $end
$scope module PC $end
$var wire 1 " clk $end
$var wire 32 V next_pc [31:0] $end
$var wire 1 # reset $end
$var reg 32 W pc [31:0] $end
$upscope $end
$scope module RF $end
$var wire 1 3 RegWrite $end
$var wire 5 X Rs [4:0] $end
$var wire 5 Y Rt [4:0] $end
$var wire 32 Z WriteData [31:0] $end
$var wire 1 " clk $end
$var wire 1 # rst $end
$var wire 32 [ ReadDataB [31:0] $end
$var wire 32 \ ReadDataA [31:0] $end
$var wire 5 ] Rd [4:0] $end
$var integer 32 ^ i [31:0] $end
$upscope $end
$scope module RegDstMux $end
$var wire 5 _ in0 [4:0] $end
$var wire 5 ` in1 [4:0] $end
$var wire 1 4 sel $end
$var wire 5 a out [4:0] $end
$upscope $end
$scope module SignExt $end
$var wire 16 b imm [15:0] $end
$var wire 32 c sign_ext_imm [31:0] $end
$upscope $end
$scope module ZeroExt $end
$var wire 16 d imm [15:0] $end
$var wire 32 e zero_ext_imm [31:0] $end
$upscope $end
$upscope $end
$upscope $end
$enddefinitions $end
#0
$dumpvars
b0xxxxxxxxxxxxxxxx e
bx d
bx c
bx b
bx a
bx `
bx _
b100000 ^
bx ]
bx \
bx [
bx Z
bx Y
bx X
bx W
bx V
bx U
bx T
bx S
bx R
bx Q
bx P
bx O
bx N
bx M
bx L
bx K
bx J
bx I
bx H
bx G
bx F
bx E
bx D
bx C
bx B
bx A
bx @
x?
bx >
x=
x<
x;
x:
bx 9
bx 8
bx 7
bx 6
bx 5
x4
x3
bx 2
bx 1
bx 0
bx /
bx .
bx -
bx ,
bx +
b0xxxxx *
bx )
bx (
x'
b0xxxxxxxxxxxxxxxx &
x%
x$
1#
0"
x!
$end
#5000
b10010001101000000000000000000 2
b10010001101000000000000000000 U
b10010001101000000000000000000 Z
b100 ,
b100 V
0'
b10010001101000000000000000000 @
b10010001101000000000000000000 K
b10010001101000000000000000000 N
b10010001101000000000000000000 S
b100100011010100 .
b0 9
b0 H
0$
b0 7
b0 P
b0 T
b1001000110100 8
b1001000110100 G
b1001000110100 I
b1001 1
b1001 D
b1001 J
b0 >
b0 E
0%
b1001000110100 0
b1001000110100 F
b0 5
b0 O
b0 [
b0 6
b0 \
b1 (
b1 ]
b1 a
b11 A
b11 C
b11 M
0=
0;
0<
13
0:
1?
04
b110100 B
b1000 *
b1001000110100 &
b1001000110100 e
b1001000110100 d
b1001000110100 )
b1001000110100 c
b1001000110100 b
b1 Y
b0 X
b10 `
b1 _
b1111 L
0!
b111100000000010001001000110100 /
b111100000000010001001000110100 R
b100 +
b0 -
b0 Q
b0 W
b100000 ^
1"
#10000
0"
#15000
b100000 ^
1"
#20000
0"
0#
#25000
b10010001101000101011001111000 2
b10010001101000101011001111000 U
b10010001101000101011001111000 Z
b10010001101000101011001111000 @
b10010001101000101011001111000 K
b10010001101000101011001111000 N
b10010001101000101011001111000 S
b101011001111000 8
b101011001111000 G
b101011001111000 I
b10010001101000000000000000000 9
b10010001101000000000000000000 H
b1010 1
b1010 D
b1010 J
b101011001111000 0
b101011001111000 F
b10010001101000000000000000000 6
b10010001101000000000000000000 \
b100 A
b100 C
b100 M
b111000 B
b11001 *
b101011001111000 &
b101011001111000 e
b101011001111000 d
b101011001111000 )
b101011001111000 c
b101011001111000 b
b1 X
b1010 `
b1101 L
b10010001101000000000000000000 >
b10010001101000000000000000000 E
b1000 ,
b1000 V
b110100001000010101011001111000 /
b110100001000010101011001111000 R
b10010001101000000000000000000 5
b10010001101000000000000000000 O
b10010001101000000000000000000 [
b10101100111101000 .
b1000 +
b100 -
b100 Q
b100 W
1"
#30000
0"
#35000
b1010 2
b1010 U
b1010 Z
b1010 8
b1010 G
b1010 I
b1010 @
b1010 K
b1010 N
b1010 S
b10 1
b10 D
b10 J
b1010 0
b1010 F
b10 (
b10 ]
b10 a
b0 A
b0 C
b0 M
b0 9
b0 H
b0 >
b0 E
b1010 B
b0 *
b1010 &
b1010 e
b1010 d
b1010 )
b1010 c
b1010 b
b10 Y
b0 X
b0 `
b10 _
b1000 L
b0 6
b0 \
b0 5
b0 O
b0 [
b1100 ,
b1100 V
b100000000000100000000000001010 /
b100000000000100000000000001010 R
b110100 .
b1100 +
b1000 -
b1000 Q
b1000 W
1"
#40000
0"
#45000
b10100 2
b10100 U
b10100 Z
b10100 @
b10100 K
b10100 N
b10100 S
b10100 8
b10100 G
b10100 I
b10100 0
b10100 F
b11 (
b11 ]
b11 a
b10100 B
b10100 &
b10100 e
b10100 d
b10100 )
b10100 c
b10100 b
b11 Y
b11 _
b0 >
b0 E
b10000 ,
b10000 V
b100000000000110000000000010100 /
b100000000000110000000000010100 R
b0 5
b0 O
b0 [
b1100000 .
b10000 +
b1100 -
b1100 Q
b1100 W
1"
#50000
0"
#55000
b11110 2
b11110 U
b11110 Z
b11110 @
b11110 K
b11110 N
b11110 S
b1010 9
b1010 H
b100 (
b100 ]
b100 a
b10000000100000 0
b10000000100000 F
b1010 6
b1010 \
b10 A
b10 C
b10 M
0?
14
b10100 >
b10100 E
b100000 B
b10000000100000 &
b10000000100000 e
b10000000100000 d
b10000000100000 )
b10000000100000 c
b10000000100000 b
b10 X
b100 `
b0 L
b10100 5
b10100 O
b10100 [
b10100 ,
b10100 V
b10000110010000000100000 /
b10000110010000000100000 R
b1000000010010100 .
b10100 +
b10000 -
b10000 Q
b10000 W
1"
#60000
0"
#65000
b1010 2
b1010 U
b1010 Z
b1010 8
b1010 G
b1010 I
0'
b1010 @
b1010 K
b1010 N
b1010 S
b1010 >
b1010 E
b10100 9
b10100 H
b110 1
b110 D
b110 J
b10100000100010 0
b10100000100010 F
b1010 5
b1010 O
b1010 [
b10100 6
b10100 \
b101 (
b101 ]
b101 a
b100010 B
b10100000100010 &
b10100000100010 e
b10100000100010 d
b10100000100010 )
b10100000100010 c
b10100000100010 b
b10 Y
b11 X
b101 `
b10 _
b11000 ,
b11000 V
b11000100010100000100010 /
b11000100010100000100010 R
b1010000010100000 .
b11000 +
b10100 -
b10100 Q
b10100 W
1"
#70000
0"
#75000
b0 2
b0 U
b0 Z
1'
b0 @
b0 K
b0 N
b0 S
b10100 8
b10100 G
b10100 I
b10100 >
b10100 E
b1010 9
b1010 H
b0 1
b0 D
b0 J
b11000000100100 0
b11000000100100 F
b10100 5
b10100 O
b10100 [
b1010 6
b1010 \
b110 (
b110 ]
b110 a
b100100 B
b11000000100100 &
b11000000100100 e
b11000000100100 d
b11000000100100 )
b11000000100100 c
b11000000100100 b
b11 Y
b10 X
b110 `
b11 _
b11100 ,
b11100 V
b10000110011000000100100 /
b10000110011000000100100 R
b1100000010101100 .
b11100 +
b11000 -
b11000 Q
b11000 W
1"
#80000
0"
#85000
b11110 2
b11110 U
b11110 Z
0'
b11110 @
b11110 K
b11110 N
b11110 S
b1 1
b1 D
b1 J
b11000000100101 0
b11000000100101 F
b100101 B
b11000000100101 &
b11000000100101 e
b11000000100101 d
b11000000100101 )
b11000000100101 c
b11000000100101 b
b100000 ,
b100000 V
b10000110011000000100101 /
b10000110011000000100101 R
b1100000010110100 .
b100000 +
b11100 -
b11100 Q
b11100 W
1"
#90000
0"
#95000
b11 1
b11 D
b11 J
b11100000100110 0
b11100000100110 F
b111 (
b111 ]
b111 a
b100110 B
b11100000100110 &
b11100000100110 e
b11100000100110 d
b11100000100110 )
b11100000100110 c
b11100000100110 b
b111 `
b100100 ,
b100100 V
b10000110011100000100110 /
b10000110011100000100110 R
b1110000010111100 .
b100100 +
b100000 -
b100000 Q
b100000 W
1"
#100000
0"
#105000
b11111111111111111111111111100001 2
b11111111111111111111111111100001 U
b11111111111111111111111111100001 Z
b11111111111111111111111111100001 @
b11111111111111111111111111100001 K
b11111111111111111111111111100001 N
b11111111111111111111111111100001 S
b1100 1
b1100 D
b1100 J
b100000000100111 0
b100000000100111 F
b1000 (
b1000 ]
b1000 a
b100111 B
b100000000100111 &
b100000000100111 e
b100000000100111 d
b100000000100111 )
b100000000100111 c
b100000000100111 b
b1000 `
b101000 ,
b101000 V
b10000110100000000100111 /
b10000110100000000100111 R
b10000000011000100 .
b101000 +
b100100 -
b100100 Q
b100100 W
1"
#110000
0"
#115000
b1 2
b1 U
b1 Z
b1 @
b1 K
b1 N
b1 S
b111 1
b111 D
b111 J
b100100000101010 0
b100100000101010 F
b1001 (
b1001 ]
b1001 a
b101010 B
b100100000101010 &
b100100000101010 e
b100100000101010 d
b100100000101010 )
b100100000101010 c
b100100000101010 b
b1001 `
b101100 ,
b101100 V
b10000110100100000101010 /
b10000110100100000101010 R
b10010000011010100 .
b101100 +
b101000 -
b101000 Q
b101000 W
1"
#120000
0"
#125000
b101000 2
b101000 U
b101000 Z
1%
b10 8
b10 G
b10 I
0'
b101000 @
b101000 K
b101000 N
b101000 S
b10 >
b10 E
b1010 9
b1010 H
b100 1
b100 D
b100 J
b101000010000000 0
b101000010000000 F
b1010 5
b1010 O
b1010 [
b0 6
b0 \
b1010 (
b1010 ]
b1010 a
b0 B
b10 *
b101000010000000 &
b101000010000000 e
b101000010000000 d
b101000010000000 )
b101000010000000 c
b101000010000000 b
b10 Y
b0 X
b1010 `
b10 _
b110000 ,
b110000 V
b100101000010000000 /
b100101000010000000 R
b10100001000110000 .
b110000 +
b101100 -
b101100 Q
b101100 W
1"
#130000
0"
#135000
b101 2
b101 U
b101 Z
b101 @
b101 K
b101 N
b101 S
b1 8
b1 G
b1 I
b101 1
b101 D
b101 J
b1 >
b1 E
b101100001000010 0
b101100001000010 F
b1011 (
b1011 ]
b1011 a
b10 B
b1 *
b101100001000010 &
b101100001000010 e
b101100001000010 d
b101100001000010 )
b101100001000010 c
b101100001000010 b
b1011 `
b110100 ,
b110100 V
b100101100001000010 /
b100101100001000010 R
b10110000100111100 .
b110100 +
b110000 -
b110000 Q
b110000 W
1"
#140000
0"
#145000
b1010 2
b1010 U
b1010 Z
b1010 @
b1010 K
b1010 N
b1010 S
b10100 9
b10100 H
b1000 1
b1000 D
b1000 J
b110000001000011 0
b110000001000011 F
b10100 5
b10100 O
b10100 [
b1100 (
b1100 ]
b1100 a
b11 B
b110000001000011 &
b110000001000011 e
b110000001000011 d
b110000001000011 )
b110000001000011 c
b110000001000011 b
b11 Y
b1100 `
b11 _
b111000 ,
b111000 V
b110110000001000011 /
b110110000001000011 R
b11000000101000100 .
b111000 +
b110100 -
b110100 Q
b110100 W
1"
#150000
0"
#155000
b0 2
b0 U
b0 Z
1'
b0 @
b0 K
b0 N
b0 S
b0 9
b0 H
b0 8
b0 G
b0 I
b10 1
b10 D
b10 J
b11110 >
b11110 E
0%
b0 0
b0 F
b11110 5
b11110 O
b11110 [
b100 (
b100 ]
b100 a
b0 A
b0 C
b0 M
1;
03
1?
04
b0 B
b0 *
b0 &
b0 e
b0 d
b0 )
b0 c
b0 b
b100 Y
b0 `
b100 _
b101011 L
b111100 ,
b111100 V
b10101100000001000000000000000000 /
b10101100000001000000000000000000 R
b111100 .
b111100 +
b111000 -
b111000 Q
b111000 W
1"
#160000
0"
#165000
b11110 2
b11110 U
b11110 Z
b101 >
b101 E
b11110 7
b11110 P
b11110 T
b101 5
b101 O
b101 [
b1011 (
b1011 ]
b1011 a
0;
1<
13
1:
b1011 Y
b1011 _
b100011 L
b1000000 ,
b1000000 V
b10001100000010110000000000000000 /
b10001100000010110000000000000000 R
b1000000 .
b1000000 +
b111100 -
b111100 Q
b111100 W
1"
#170000
0"
#175000
b11110 9
b11110 H
1$
b0 7
b0 P
b0 T
b0 2
b0 U
b0 Z
b11110 8
b11110 G
b11110 I
b110 1
b110 D
b110 J
b1 0
b1 F
b11110 6
b11110 \
b100 (
b100 ]
b100 a
b1 A
b1 C
b1 M
1=
0<
03
0:
0?
b11110 >
b11110 E
b1 B
b1 &
b1 e
b1 d
b1 )
b1 c
b1 b
b100 Y
b1011 X
b100 _
b100 L
b11110 5
b11110 O
b11110 [
b1001000 ,
b1001000 V
b10001011001000000000000000001 /
b10001011001000000000000000001 R
b1001000 .
b1000100 +
b1000000 -
b1000000 Q
b1000000 W
1"
#180000
0"
#185000
b0 2
b0 U
b0 Z
b0 8
b0 G
b0 I
1'
b0 @
b0 K
b0 N
b0 S
b0 >
b0 E
b0 9
b0 H
0$
b10 1
b10 D
b10 J
b11111111111111111111111111111111 0
b11111111111111111111111111111111 F
b0 5
b0 O
b0 [
b0 6
b0 \
b11111 (
b11111 ]
b11111 a
b0 A
b0 C
b0 M
0=
b111111 B
b11111 *
b1111111111111111 &
b1111111111111111 e
b1111111111111111 d
b11111111111111111111111111111111 )
b11111111111111111111111111111111 c
b1111111111111111 b
b11111 Y
b11111 X
b11111 `
b11111 _
b111111 L
b1001100 ,
b1001100 V
1!
b11111111111111111111111111111111 /
b11111111111111111111111111111111 R
b1001000 .
b1001100 +
b1001000 -
b1001000 Q
b1001000 W
1"
#190000
0"
#195000
bx 2
bx U
bx Z
bx 8
bx G
bx I
x'
bx @
bx K
bx N
bx S
x%
bx >
bx E
bx 9
bx H
bx 0
bx F
bx 5
bx O
bx [
bx 6
bx \
bx (
bx ]
bx a
bx B
b0xxxxx *
b0xxxxxxxxxxxxxxxx &
b0xxxxxxxxxxxxxxxx e
bx d
bx )
bx c
bx b
bx Y
bx X
bx `
bx _
bx L
b1010000 ,
b1010000 V
x!
bx /
bx R
bx .
b1010000 +
b1001100 -
b1001100 Q
b1001100 W
1"
#200000
0"
#205000
b1010100 ,
b1010100 V
b1010100 +
b1010000 -
b1010000 Q
b1010000 W
1"
